toml_template/__init__.py
toml_template/exceptions.py
toml_template-1.0.2.dist-info/LICENSE
toml_template-1.0.2.dist-info/METADATA
toml_template-1.0.2.dist-info/WHEEL
toml_template-1.0.2.dist-info/top_level.txt
toml_template-1.0.2.dist-info/RECORD
